kubedev/__init__.py
kubedev/__main__.py
kubedev/command_line.py
kubedev/kubedev.py
kubedev/templates/Dockerfile
kubedev/templates/Dockerfile_pipenv
kubedev/templates/Pipfile
kubedev/templates/Pipfile.lock
kubedev/templates/app.py
kubedev/templates/helm-chart/Chart.yaml
kubedev/templates/helm-chart/cronjob.yaml
kubedev/templates/helm-chart/deployment.yaml
kubedev/templates/helm-chart/service.yaml
kubedev/utils/__init__.py
kubedev/utils/errors.py
kubedev/utils/kubedev_config.py
kubedev/utils/kubernetes_tools.py
kubedev/utils/yaml_merger.py
kubedev-0.42.74.dist-info/LICENSE
kubedev-0.42.74.dist-info/METADATA
kubedev-0.42.74.dist-info/WHEEL
kubedev-0.42.74.dist-info/entry_points.txt
kubedev-0.42.74.dist-info/top_level.txt
kubedev-0.42.74.dist-info/RECORD
