Metadata-Version: 2.1
Name: kubedev
Version: 0.42.74
Summary: Kubernetes development workflow made easy
Home-page: https://gitlab.com/daniel.albuschat.gira/kubedev
Author: Daniel Albuschat
Author-email: d.albuschat@gmail.com
Classifier: Programming Language :: Python :: 3
Classifier: License :: OSI Approved :: MIT License
Classifier: Operating System :: OS Independent
Requires-Python: >=3.6
License-File: LICENSE
Requires-Dist: pyyaml
Requires-Dist: ruamel-yaml
Requires-Dist: colorama
Requires-Dist: requests
